legistar/__init__.py
legistar/base.py
legistar/bills.py
legistar/events.py
legistar/people.py
scraper_legistar-0.0.2.dist-info/licenses/AUTHORS
scraper_legistar-0.0.2.dist-info/licenses/LICENSE
scraper_legistar-0.0.2.dist-info/METADATA
scraper_legistar-0.0.2.dist-info/WHEEL
scraper_legistar-0.0.2.dist-info/top_level.txt
scraper_legistar-0.0.2.dist-info/RECORD
