Metadata-Version: 2.4
Name: scraper-legistar
Version: 0.0.2
Summary: Mixin classes for legistar scrapers
Home-page: http://github.com/opencivicdata/python-legistar-scraper/
Author: Forest Gregg
Author-email: fgregg@datamade.us
License: BSD
Platform: any
Classifier: Development Status :: 4 - Beta
Classifier: Intended Audience :: Developers
Classifier: License :: OSI Approved :: BSD License
Classifier: Natural Language :: English
Classifier: Operating System :: OS Independent
Classifier: Programming Language :: Python :: 3.3
Classifier: Programming Language :: Python :: 3.4
Classifier: Topic :: Software Development :: Libraries :: Python Modules
License-File: LICENSE
License-File: AUTHORS
Requires-Dist: requests
Requires-Dist: lxml
Requires-Dist: pytz
Requires-Dist: icalendar
Requires-Dist: scrapelib
Requires-Dist: esprima
Dynamic: author
Dynamic: author-email
Dynamic: classifier
Dynamic: home-page
Dynamic: license
Dynamic: license-file
Dynamic: platform
Dynamic: requires-dist
Dynamic: summary
